MANIFEST.in
README.rst
setup.py
collective/.DS_Store
collective/__init__.py
collective/__init__.pyc
collective.ptg.tile.egg-info/PKG-INFO
collective.ptg.tile.egg-info/SOURCES.txt
collective.ptg.tile.egg-info/dependency_links.txt
collective.ptg.tile.egg-info/entry_points.txt
collective.ptg.tile.egg-info/namespace_packages.txt
collective.ptg.tile.egg-info/not-zip-safe
collective.ptg.tile.egg-info/requires.txt
collective.ptg.tile.egg-info/top_level.txt
collective/ptg/.DS_Store
collective/ptg/__init__.py
collective/ptg/__init__.pyc
collective/ptg/tile/.DS_Store
collective/ptg/tile/__init__.py
collective/ptg/tile/__init__.pyc
collective/ptg/tile/configure.zcml
collective/ptg/tile/ptg_tile.pt
collective/ptg/tile/ptg_tile.py
collective/ptg/tile/ptg_tile.pyc
collective/ptg/tile/vocabularies.py
collective/ptg/tile/vocabularies.pyc
collective/ptg/tile/files/ptg_tile.png
collective/ptg/tile/profiles/.DS_Store
collective/ptg/tile/profiles/default/metadata.xml
collective/ptg/tile/profiles/default/registry.xml
docs/HISTORY.txt
docs/LICENSE.GPL
docs/LICENSE.txt