Metadata-Version: 1.1
Name: collective.ptg.tile
Version: 0.1b1
Summary: Trueghallery tile for collective.cover
Home-page: https://github.com/espenmn/collective.ptg.tile
Author: Espen Moe-Nilssen
Author-email: espen@medialog.no
License: GPL
Keywords: collective cover truegallery
Platform: UNKNOWN
Classifier: Framework :: Plone
Classifier: Programming Language :: Python
